cli/clip.py
cli/faces.py
cli/metadata.py
cli/motion.py
cli/objects.py
cli/ocr.py
cli/scenes.py
cli/telemetry.py
cli/transcript.py
media_engine/__init__.py
media_engine/_version.py
media_engine/app.py
media_engine/cli.py
media_engine/config.py
media_engine/main.py
media_engine/py.typed
media_engine/schemas.py
media_engine/batch/__init__.py
media_engine/batch/models.py
media_engine/batch/processor.py
media_engine/batch/queue.py
media_engine/batch/state.py
media_engine/batch/timing.py
media_engine/extractors/__init__.py
media_engine/extractors/clip.py
media_engine/extractors/faces.py
media_engine/extractors/frame_buffer.py
media_engine/extractors/frames.py
media_engine/extractors/motion.py
media_engine/extractors/objects.py
media_engine/extractors/objects_qwen.py
media_engine/extractors/ocr.py
media_engine/extractors/scenes.py
media_engine/extractors/shot_type.py
media_engine/extractors/telemetry.py
media_engine/extractors/transcribe.py
media_engine/extractors/translate.py
media_engine/extractors/vad.py
media_engine/extractors/metadata/__init__.py
media_engine/extractors/metadata/apple.py
media_engine/extractors/metadata/arri.py
media_engine/extractors/metadata/avchd.py
media_engine/extractors/metadata/avchd_gps.py
media_engine/extractors/metadata/base.py
media_engine/extractors/metadata/blackmagic.py
media_engine/extractors/metadata/camera_360.py
media_engine/extractors/metadata/canon.py
media_engine/extractors/metadata/dji.py
media_engine/extractors/metadata/dv.py
media_engine/extractors/metadata/ffmpeg.py
media_engine/extractors/metadata/generic.py
media_engine/extractors/metadata/gopro.py
media_engine/extractors/metadata/red.py
media_engine/extractors/metadata/registry.py
media_engine/extractors/metadata/sony.py
media_engine/extractors/metadata/tesla.py
media_engine/routers/__init__.py
media_engine/routers/batch.py
media_engine/routers/health.py
media_engine/routers/models.py
media_engine/routers/settings.py
media_engine/routers/utils.py
media_engine-0.1.0.dist-info/METADATA
media_engine-0.1.0.dist-info/WHEEL
media_engine-0.1.0.dist-info/entry_points.txt
media_engine-0.1.0.dist-info/licenses/LICENSE
media_engine-0.1.0.dist-info/RECORD
