Metadata-Version: 2.4
Name: media-engine
Version: 0.1.0
Summary: AI-powered video extraction API for metadata, transcripts, faces, scenes, objects, and more
Project-URL: Repository, https://github.com/thetrainroom/media-engine
Project-URL: Issues, https://github.com/thetrainroom/media-engine/issues
License: MIT
License-File: LICENSE
Keywords: ai,extraction,faces,metadata,ml,ocr,scenes,transcription,video
Classifier: Development Status :: 4 - Beta
Classifier: Framework :: FastAPI
Classifier: License :: OSI Approved :: MIT License
Classifier: Operating System :: MacOS :: MacOS X
Classifier: Operating System :: POSIX :: Linux
Classifier: Programming Language :: Python :: 3.12
Classifier: Programming Language :: Python :: 3.13
Classifier: Topic :: Multimedia :: Video
Classifier: Topic :: Scientific/Engineering :: Artificial Intelligence
Requires-Python: >=3.12
Requires-Dist: deepface>=0.0.79
Requires-Dist: fastapi>=0.109.0
Requires-Dist: ffmpeg-python>=0.2.0
Requires-Dist: httpx>=0.27.0
Requires-Dist: langdetect>=1.0.9
Requires-Dist: paddleocr>=2.7.0
Requires-Dist: paddlepaddle>=2.5.0
Requires-Dist: psutil>=5.9.0
Requires-Dist: pydantic-settings>=2.0.0
Requires-Dist: pydantic>=2.0.0
Requires-Dist: scenedetect[opencv]>=0.6.0
Requires-Dist: uvicorn>=0.27.0
Requires-Dist: webrtcvad>=2.0.10
Provides-Extra: cpu
Requires-Dist: open-clip-torch>=2.24.0; extra == 'cpu'
Requires-Dist: openai-whisper>=20231117; extra == 'cpu'
Requires-Dist: torch>=2.0.0; extra == 'cpu'
Requires-Dist: ultralytics>=8.0.0; extra == 'cpu'
Provides-Extra: cuda
Requires-Dist: faster-whisper>=0.10.0; extra == 'cuda'
Requires-Dist: open-clip-torch>=2.24.0; extra == 'cuda'
Requires-Dist: torch>=2.0.0; extra == 'cuda'
Requires-Dist: ultralytics>=8.0.0; extra == 'cuda'
Provides-Extra: dev
Requires-Dist: black>=24.0.0; extra == 'dev'
Requires-Dist: httpx>=0.27.0; extra == 'dev'
Requires-Dist: pyright>=1.1.0; extra == 'dev'
Requires-Dist: pytest-asyncio>=0.23.0; extra == 'dev'
Requires-Dist: pytest-cov>=4.0.0; extra == 'dev'
Requires-Dist: pytest>=8.0.0; extra == 'dev'
Requires-Dist: ruff>=0.3.0; extra == 'dev'
Provides-Extra: mlx
Requires-Dist: mlx-whisper>=0.4.0; extra == 'mlx'
Requires-Dist: mlx>=0.5.0; extra == 'mlx'
Requires-Dist: open-clip-torch>=2.24.0; extra == 'mlx'
Requires-Dist: torch>=2.0.0; extra == 'mlx'
Requires-Dist: ultralytics>=8.0.0; extra == 'mlx'
Provides-Extra: qwen
Requires-Dist: accelerate>=0.30.0; extra == 'qwen'
Requires-Dist: qwen-vl-utils>=0.0.8; extra == 'qwen'
Requires-Dist: torch>=2.0.0; extra == 'qwen'
Requires-Dist: transformers>=4.40.0; extra == 'qwen'
